MANIFEST.in
README.rst
setup.py
aliyun_python_sdk_cloudmarketing.egg-info/PKG-INFO
aliyun_python_sdk_cloudmarketing.egg-info/SOURCES.txt
aliyun_python_sdk_cloudmarketing.egg-info/dependency_links.txt
aliyun_python_sdk_cloudmarketing.egg-info/requires.txt
aliyun_python_sdk_cloudmarketing.egg-info/top_level.txt
aliyunsdkcloudmarketing/__init__.py
aliyunsdkcloudmarketing/request/__init__.py
aliyunsdkcloudmarketing/request/v20180910/AnalysisCrowdRequest.py
aliyunsdkcloudmarketing/request/v20180910/Auth2BrandRequest.py
aliyunsdkcloudmarketing/request/v20180910/CalCrowdScaleRequest.py
aliyunsdkcloudmarketing/request/v20180910/CreateBrandRequest.py
aliyunsdkcloudmarketing/request/v20180910/CreateCategoryRequest.py
aliyunsdkcloudmarketing/request/v20180910/DefineCrowdRequest.py
aliyunsdkcloudmarketing/request/v20180910/DefineFileSchemaRequest.py
aliyunsdkcloudmarketing/request/v20180910/DefineTagRequest.py
aliyunsdkcloudmarketing/request/v20180910/DeleteCrowdRequest.py
aliyunsdkcloudmarketing/request/v20180910/DeleteFileRequest.py
aliyunsdkcloudmarketing/request/v20180910/DescribeAuthBrandRequest.py
aliyunsdkcloudmarketing/request/v20180910/DescribeAuthChannelBrandRequest.py
aliyunsdkcloudmarketing/request/v20180910/DescribeBrandRequest.py
aliyunsdkcloudmarketing/request/v20180910/DescribeCategoryRequest.py
aliyunsdkcloudmarketing/request/v20180910/DescribeChannelBrandRequest.py
aliyunsdkcloudmarketing/request/v20180910/DescribeCrowdRequest.py
aliyunsdkcloudmarketing/request/v20180910/DescribeFileRequest.py
aliyunsdkcloudmarketing/request/v20180910/DescribeTagRequest.py
aliyunsdkcloudmarketing/request/v20180910/DownloadCrowdRequest.py
aliyunsdkcloudmarketing/request/v20180910/DownloadUDReportRequest.py
aliyunsdkcloudmarketing/request/v20180910/FavoriteTagRequest.py
aliyunsdkcloudmarketing/request/v20180910/FetchCrowdDefineRequest.py
aliyunsdkcloudmarketing/request/v20180910/FetchCrowdRequest.py
aliyunsdkcloudmarketing/request/v20180910/FetchFileSchemaDataRequest.py
aliyunsdkcloudmarketing/request/v20180910/FetchFileSchemaRequest.py
aliyunsdkcloudmarketing/request/v20180910/FetchTagRequest.py
aliyunsdkcloudmarketing/request/v20180910/ProcessAfterUploadFileRequest.py
aliyunsdkcloudmarketing/request/v20180910/RedefineTagRequest.py
